Workbook

Sheet How to use
B2: EP Loan Payments: interim worksheet
B3: The Investment team records payments here. EP Central reads this sheet every day and updates Loans Performance. Loans themselves are created and edited in EP Central, not here.
B5: Which cells to edit
B6: Yellow, blue text | C6: You fill these in: Loan UID, payment no., date, amounts, tranche, invoice link, comments.
B7: Grey | C7: Fills itself from what you typed: company, loan, payment total, check. Do not type here.
B8: Light blue | C8: Written by EP Central: sync status and time, and the whole Loans (reference) tab. Do not type here.
B10: How to record a payment
B11: 1. New loan? | C11: Create it in EP Central first (Reports > Loans Performance > Create > New loan, or New loan on the company page). EP Central generates the Loan UID, or you can paste one you already issued. After the next sync it appears in the Loans (reference) tab.
B12: 2. Add one row per payment | C12: On the Payments tab, pick the Loan UID. Company and loan fill in so you can check you picked the right one.
B13: 3. Payment no. and date | C13: Use the next payment number for that loan (the Loans tab shows the last number EP Central has). Enter the date the payment was received.
B14: 4. Amounts | C14: Interest, principal and any other fee, as numbers without the $ sign. Payment total adds them up. Revenue is for RBF loans only.
B15: 5. Check column | C15: "Ready" means the row is complete. Anything else says what is missing.
B16: 6. Sync | C16: EP Central imports Ready rows every day at 08:00 UTC, or straight away with Data Sync in Reports > Loans Performance. Sync status then shows Imported, Updated, or Error with the reason.
B18: Rules
B19: Correcting a payment | C19: Change the row and keep the same Loan UID and payment no. The next sync updates the payment in EP Central.
B20: Removing a payment | C20: Deleting a row here does not delete the payment. Remove it in EP Central (it is logged there).
B21: What EP Central calculates | C21: Principal repaid, interest repaid, balance outstanding, the monthly principal and interest grids and the portfolio totals all come from these rows. Nothing else needs to be typed.
B22: Example rows | C22: Rows 2 to 4 on the Payments tab are examples with sample data. Delete them before real use. The Loans (reference) rows are sample data too.

Sheet Payments
A1: Loan UID | B1: Company | C1: Loan | D1: Payment no. | E1: Payment date | F1: Interest ($) | G1: Principal ($) | H1: Other fee ($) | I1: Revenue ($) RBF only | J1: Payment total ($) | K1: Tranche | L1: Invoice link | M1: Comments | N1: Check | O1: Sync status | P1: Synced at
A2: b92edd73-c32e-55f7-8064-a27e9236b043 | B2: =IF($A2="","",IFERROR(INDEX('Loans (reference)'!$B$2:$B$500,MATCH($A2,'Loans (reference)'!$A$2:$A$500,0)),"not found")) -> fourstars | C2: =IF($A2="","",IFERROR(INDEX('Loans (reference)'!$K$2:$K$500,MATCH($A2,'Loans (reference)'!$A$2:$A$500,0)),"")) -> CGA · ECF2 · #3 | D2: 11 | E2: 46265 | F2: 14268.8 | G2: 66666.4 | J2: =IF(COUNT($F2:$H2)=0,"",SUM($F2:$H2)) -> 80935.2 | K2: 1 | L2: https://docs.google.com/spreadsheets/d/EXAMPLE | M2: EXAMPLE ROW - delete before use | N2: =IF(COUNTA($A2,$D2:$I2,$K2:$M2)=0,"",IF($A2="","Add Loan UID",IF(ISNA(MATCH($A2,'Loans (reference)'!$A$2:$A$500,0)),"UID not in Loans tab",IF($D2="","Add payment no.",IF(COUNTIFS($A$2:$A$300,$A2,$D$2:$D$300,$D2)>1,"Duplicate payment no.",IF($E2="","Add payment date",IF(COUNT($F2:$H2)=0,"Add an amount","Ready"))))))) -> Ready | O2: Imported | P2: 46266.333
A3: da903dec-65df-5064-9d90-d31a087e3e44 | B3: =IF($A3="","",IFERROR(INDEX('Loans (reference)'!$B$2:$B$500,MATCH($A3,'Loans (reference)'!$A$2:$A$500,0)),"not found")) -> Summit Heat Pumps | C3: =IF($A3="","",IFERROR(INDEX('Loans (reference)'!$K$2:$K$500,MATCH($A3,'Loans (reference)'!$A$2:$A$500,0)),"")) -> TRL · ECF2 · #2 | D3: 11 | E3: 46265 | F3: 14268.8 | G3: 66666.4 | J3: =IF(COUNT($F3:$H3)=0,"",SUM($F3:$H3)) -> 80935.2 | K3: 1 | M3: EXAMPLE ROW - delete before use | N3: =IF(COUNTA($A3,$D3:$I3,$K3:$M3)=0,"",IF($A3="","Add Loan UID",IF(ISNA(MATCH($A3,'Loans (reference)'!$A$2:$A$500,0)),"UID not in Loans tab",IF($D3="","Add payment no.",IF(COUNTIFS($A$2:$A$300,$A3,$D$2:$D$300,$D3)>1,"Duplicate payment no.",IF($E3="","Add payment date",IF(COUNT($F3:$H3)=0,"Add an amount","Ready"))))))) -> Ready
A4: caa72316-ceb7-5244-bf17-907cfa7d4856 | B4: =IF($A4="","",IFERROR(INDEX('Loans (reference)'!$B$2:$B$500,MATCH($A4,'Loans (reference)'!$A$2:$A$500,0)),"not found")) -> Kinetiq | C4: =IF($A4="","",IFERROR(INDEX('Loans (reference)'!$K$2:$K$500,MATCH($A4,'Loans (reference)'!$A$2:$A$500,0)),"")) -> RBF · ECF1 · #1 | D4: 45 | E4: 46270 | F4: 1187.56 | G4: 10556.14 | I4: 263903.3 | J4: =IF(COUNT($F4:$H4)=0,"",SUM($F4:$H4)) -> 11743.7 | M4: EXAMPLE ROW - delete before use (RBF: revenue filled in) | N4: =IF(COUNTA($A4,$D4:$I4,$K4:$M4)=0,"",IF($A4="","Add Loan UID",IF(ISNA(MATCH($A4,'Loans (reference)'!$A$2:$A$500,0)),"UID not in Loans tab",IF($D4="","Add payment no.",IF(COUNTIFS($A$2:$A$300,$A4,$D$2:$D$300,$D4)>1,"Duplicate payment no.",IF($E4="","Add payment date",IF(COUNT($F4:$H4)=0,"Add an amount","Ready"))))))) -> Ready
B5: =IF($A5="","",IFERROR(INDEX('Loans (reference)'!$B$2:$B$500,MATCH($A5,'Loans (reference)'!$A$2:$A$500,0)),"not found")) | C5: =IF($A5="","",IFERROR(INDEX('Loans (reference)'!$K$2:$K$500,MATCH($A5,'Loans (reference)'!$A$2:$A$500,0)),"")) | J5: =IF(COUNT($F5:$H5)=0,"",SUM($F5:$H5)) | N5: =IF(COUNTA($A5,$D5:$I5,$K5:$M5)=0,"",IF($A5="","Add Loan UID",IF(ISNA(MATCH($A5,'Loans (reference)'!$A$2:$A$500,0)),"UID not in Loans tab",IF($D5="","Add payment no.",IF(COUNTIFS($A$2:$A$300,$A5,$D$2:$D$300,$D5)>1,"Duplicate payment no.",IF($E5="","Add payment date",IF(COUNT($F5:$H5)=0,"Add an amount","Ready")))))))
B6: =IF($A6="","",IFERROR(INDEX('Loans (reference)'!$B$2:$B$500,MATCH($A6,'Loans (reference)'!$A$2:$A$500,0)),"not found")) | C6: =IF($A6="","",IFERROR(INDEX('Loans (reference)'!$K$2:$K$500,MATCH($A6,'Loans (reference)'!$A$2:$A$500,0)),"")) | J6: =IF(COUNT($F6:$H6)=0,"",SUM($F6:$H6)) | N6: =IF(COUNTA($A6,$D6:$I6,$K6:$M6)=0,"",IF($A6="","Add Loan UID",IF(ISNA(MATCH($A6,'Loans (reference)'!$A$2:$A$500,0)),"UID not in Loans tab",IF($D6="","Add payment no.",IF(COUNTIFS($A$2:$A$300,$A6,$D$2:$D$300,$D6)>1,"Duplicate payment no.",IF($E6="","Add payment date",IF(COUNT($F6:$H6)=0,"Add an amount","Ready")))))))
B7: =IF($A7="","",IFERROR(INDEX('Loans (reference)'!$B$2:$B$500,MATCH($A7,'Loans (reference)'!$A$2:$A$500,0)),"not found")) | C7: =IF($A7="","",IFERROR(INDEX('Loans (reference)'!$K$2:$K$500,MATCH($A7,'Loans (reference)'!$A$2:$A$500,0)),"")) | J7: =IF(COUNT($F7:$H7)=0,"",SUM($F7:$H7)) | N7: =IF(COUNTA($A7,$D7:$I7,$K7:$M7)=0,"",IF($A7="","Add Loan UID",IF(ISNA(MATCH($A7,'Loans (reference)'!$A$2:$A$500,0)),"UID not in Loans tab",IF($D7="","Add payment no.",IF(COUNTIFS($A$2:$A$300,$A7,$D$2:$D$300,$D7)>1,"Duplicate payment no.",IF($E7="","Add payment date",IF(COUNT($F7:$H7)=0,"Add an amount","Ready")))))))
B8: =IF($A8="","",IFERROR(INDEX('Loans (reference)'!$B$2:$B$500,MATCH($A8,'Loans (reference)'!$A$2:$A$500,0)),"not found")) | C8: =IF($A8="","",IFERROR(INDEX('Loans (reference)'!$K$2:$K$500,MATCH($A8,'Loans (reference)'!$A$2:$A$500,0)),"")) | J8: =IF(COUNT($F8:$H8)=0,"",SUM($F8:$H8)) | N8: =IF(COUNTA($A8,$D8:$I8,$K8:$M8)=0,"",IF($A8="","Add Loan UID",IF(ISNA(MATCH($A8,'Loans (reference)'!$A$2:$A$500,0)),"UID not in Loans tab",IF($D8="","Add payment no.",IF(COUNTIFS($A$2:$A$300,$A8,$D$2:$D$300,$D8)>1,"Duplicate payment no.",IF($E8="","Add payment date",IF(COUNT($F8:$H8)=0,"Add an amount","Ready")))))))
B9: =IF($A9="","",IFERROR(INDEX('Loans (reference)'!$B$2:$B$500,MATCH($A9,'Loans (reference)'!$A$2:$A$500,0)),"not found")) | C9: =IF($A9="","",IFERROR(INDEX('Loans (reference)'!$K$2:$K$500,MATCH($A9,'Loans (reference)'!$A$2:$A$500,0)),"")) | J9: =IF(COUNT($F9:$H9)=0,"",SUM($F9:$H9)) | N9: =IF(COUNTA($A9,$D9:$I9,$K9:$M9)=0,"",IF($A9="","Add Loan UID",IF(ISNA(MATCH($A9,'Loans (reference)'!$A$2:$A$500,0)),"UID not in Loans tab",IF($D9="","Add payment no.",IF(COUNTIFS($A$2:$A$300,$A9,$D$2:$D$300,$D9)>1,"Duplicate payment no.",IF($E9="","Add payment date",IF(COUNT($F9:$H9)=0,"Add an amount","Ready")))))))
B10: =IF($A10="","",IFERROR(INDEX('Loans (reference)'!$B$2:$B$500,MATCH($A10,'Loans (reference)'!$A$2:$A$500,0)),"not found")) | C10: =IF($A10="","",IFERROR(INDEX('Loans (reference)'!$K$2:$K$500,MATCH($A10,'Loans (reference)'!$A$2:$A$500,0)),"")) | J10: =IF(COUNT($F10:$H10)=0,"",SUM($F10:$H10)) | N10: =IF(COUNTA($A10,$D10:$I10,$K10:$M10)=0,"",IF($A10="","Add Loan UID",IF(ISNA(MATCH($A10,'Loans (reference)'!$A$2:$A$500,0)),"UID not in Loans tab",IF($D10="","Add payment no.",IF(COUNTIFS($A$2:$A$300,$A10,$D$2:$D$300,$D10)>1,"Duplicate payment no.",IF($E10="","Add payment date",IF(COUNT($F10:$H10)=0,"Add an amount","Ready")))))))
B11: =IF($A11="","",IFERROR(INDEX('Loans (reference)'!$B$2:$B$500,MATCH($A11,'Loans (reference)'!$A$2:$A$500,0)),"not found")) | C11: =IF($A11="","",IFERROR(INDEX('Loans (reference)'!$K$2:$K$500,MATCH($A11,'Loans (reference)'!$A$2:$A$500,0)),"")) | J11: =IF(COUNT($F11:$H11)=0,"",SUM($F11:$H11)) | N11: =IF(COUNTA($A11,$D11:$I11,$K11:$M11)=0,"",IF($A11="","Add Loan UID",IF(ISNA(MATCH($A11,'Loans (reference)'!$A$2:$A$500,0)),"UID not in Loans tab",IF($D11="","Add payment no.",IF(COUNTIFS($A$2:$A$300,$A11,$D$2:$D$300,$D11)>1,"Duplicate payment no.",IF($E11="","Add payment date",IF(COUNT($F11:$H11)=0,"Add an amount","Ready")))))))
B12: =IF($A12="","",IFERROR(INDEX('Loans (reference)'!$B$2:$B$500,MATCH($A12,'Loans (reference)'!$A$2:$A$500,0)),"not found")) | C12: =IF($A12="","",IFERROR(INDEX('Loans (reference)'!$K$2:$K$500,MATCH($A12,'Loans (reference)'!$A$2:$A$500,0)),"")) | J12: =IF(COUNT($F12:$H12)=0,"",SUM($F12:$H12)) | N12: =IF(COUNTA($A12,$D12:$I12,$K12:$M12)=0,"",IF($A12="","Add Loan UID",IF(ISNA(MATCH($A12,'Loans (reference)'!$A$2:$A$500,0)),"UID not in Loans tab",IF($D12="","Add payment no.",IF(COUNTIFS($A$2:$A$300,$A12,$D$2:$D$300,$D12)>1,"Duplicate payment no.",IF($E12="","Add payment date",IF(COUNT($F12:$H12)=0,"Add an amount","Ready")))))))
B13: =IF($A13="","",IFERROR(INDEX('Loans (reference)'!$B$2:$B$500,MATCH($A13,'Loans (reference)'!$A$2:$A$500,0)),"not found")) | C13: =IF($A13="","",IFERROR(INDEX('Loans (reference)'!$K$2:$K$500,MATCH($A13,'Loans (reference)'!$A$2:$A$500,0)),"")) | J13: =IF(COUNT($F13:$H13)=0,"",SUM($F13:$H13)) | N13: =IF(COUNTA($A13,$D13:$I13,$K13:$M13)=0,"",IF($A13="","Add Loan UID",IF(ISNA(MATCH($A13,'Loans (reference)'!$A$2:$A$500,0)),"UID not in Loans tab",IF($D13="","Add payment no.",IF(COUNTIFS($A$2:$A$300,$A13,$D$2:$D$300,$D13)>1,"Duplicate payment no.",IF($E13="","Add payment date",IF(COUNT($F13:$H13)=0,"Add an amount","Ready")))))))
B14: =IF($A14="","",IFERROR(INDEX('Loans (reference)'!$B$2:$B$500,MATCH($A14,'Loans (reference)'!$A$2:$A$500,0)),"not found")) | C14: =IF($A14="","",IFERROR(INDEX('Loans (reference)'!$K$2:$K$500,MATCH($A14,'Loans (reference)'!$A$2:$A$500,0)),"")) | J14: =IF(COUNT($F14:$H14)=0,"",SUM($F14:$H14)) | N14: =IF(COUNTA($A14,$D14:$I14,$K14:$M14)=0,"",IF($A14="","Add Loan UID",IF(ISNA(MATCH($A14,'Loans (reference)'!$A$2:$A$500,0)),"UID not in Loans tab",IF($D14="","Add payment no.",IF(COUNTIFS($A$2:$A$300,$A14,$D$2:$D$300,$D14)>1,"Duplicate payment no.",IF($E14="","Add payment date",IF(COUNT($F14:$H14)=0,"Add an amount","Ready")))))))
B15: =IF($A15="","",IFERROR(INDEX('Loans (reference)'!$B$2:$B$500,MATCH($A15,'Loans (reference)'!$A$2:$A$500,0)),"not found")) | C15: =IF($A15="","",IFERROR(INDEX('Loans (reference)'!$K$2:$K$500,MATCH($A15,'Loans (reference)'!$A$2:$A$500,0)),"")) | J15: =IF(COUNT($F15:$H15)=0,"",SUM($F15:$H15)) | N15: =IF(COUNTA($A15,$D15:$I15,$K15:$M15)=0,"",IF($A15="","Add Loan UID",IF(ISNA(MATCH($A15,'Loans (reference)'!$A$2:$A$500,0)),"UID not in Loans tab",IF($D15="","Add payment no.",IF(COUNTIFS($A$2:$A$300,$A15,$D$2:$D$300,$D15)>1,"Duplicate payment no.",IF($E15="","Add payment date",IF(COUNT($F15:$H15)=0,"Add an amount","Ready")))))))
B16: =IF($A16="","",IFERROR(INDEX('Loans (reference)'!$B$2:$B$500,MATCH($A16,'Loans (reference)'!$A$2:$A$500,0)),"not found")) | C16: =IF($A16="","",IFERROR(INDEX('Loans (reference)'!$K$2:$K$500,MATCH($A16,'Loans (reference)'!$A$2:$A$500,0)),"")) | J16: =IF(COUNT($F16:$H16)=0,"",SUM($F16:$H16)) | N16: =IF(COUNTA($A16,$D16:$I16,$K16:$M16)=0,"",IF($A16="","Add Loan UID",IF(ISNA(MATCH($A16,'Loans (reference)'!$A$2:$A$500,0)),"UID not in Loans tab",IF($D16="","Add payment no.",IF(COUNTIFS($A$2:$A$300,$A16,$D$2:$D$300,$D16)>1,"Duplicate payment no.",IF($E16="","Add payment date",IF(COUNT($F16:$H16)=0,"Add an amount","Ready")))))))
... B300: =IF($A300="","",IFERROR(INDEX('Loans (reference)'!$B$2:$B$500,MATCH($A300,'Loans (reference)'!$A$2:$A$500,0)),"not found")) | C300: =IF($A300="","",IFERROR(INDEX('Loans (reference)'!$K$2:$K$500,MATCH($A300,'Loans (reference)'!$A$2:$A$500,0)),"")) | J300: =IF(COUNT($F300:$H300)=0,"",SUM($F300:$H300)) | N300: =IF(COUNTA($A300,$D300:$I300,$K300:$M300)=0,"",IF($A300="","Add Loan UID",IF(ISNA(MATCH($A300,'Loans (reference)'!$A$2:$A$500,0)),"UID not in Loans tab",IF($D300="","Add payment no.",IF(COUNTIFS($A$2:$A$300,$A300,$D$2:$D$300,$D300)>1,"Duplicate payment no.",IF($E300="","Add payment date",IF(COUNT($F300:$H300)=0,"Add an amount","Ready")))))))

Sheet Loans (reference)
A1: Loan UID | B1: Company | C1: Product | D1: Type | E1: Fund | F1: Loan no. | G1: Status | H1: Loan size ($) | I1: Principal outstanding ($) | J1: Last payment no. in EP Central | K1: Loan (label) | M1: Do not edit this tab.
A2: b92edd73-c32e-55f7-8064-a27e9236b043 | B2: fourstars | C2: Funding #3 | D2: CGA | E2: ECF2 | F2: 3 | G2: Active | H2: 200000 | I2: 133333 | J2: 10 | K2: =D2&" · "&E2&" · #"&F2 -> CGA · ECF2 · #3 | M2: EP Central rewrites it at every sync, so a loan created in EP Central appears here with its UID.
A3: da903dec-65df-5064-9d90-d31a087e3e44 | B3: Summit Heat Pumps | C3: Funding #2 | D3: TRL | E3: ECF2 | F3: 2 | G3: Active | H3: 1600000 | I3: 1133333 | J3: 10 | K3: =D3&" · "&E3&" · #"&F3 -> TRL · ECF2 · #2 | M3: Rows shown are sample data.
A4: af336409-cad4-51c3-873f-99ceb6887000 | B4: Soilworks Company | C4: Funding #1 | D4: CGA | E4: ECF2 | F4: 1 | G4: Active | H4: 480000 | I4: 480000 | J4: 12 | K4: =D4&" · "&E4&" · #"&F4 -> CGA · ECF2 · #1
A5: 7e2a073d-c5df-5d35-b461-575f40191d57 | B5: Tidal Marine | C5: Funding #1 | D5: CGA | E5: ECF2 | F5: 1 | G5: Active | H5: 800000 | I5: 86547 | J5: 12 | K5: =D5&" · "&E5&" · #"&F5 -> CGA · ECF2 · #1
A6: ee1e88a2-0693-504c-949b-873428514324 | B6: Prairie Insulation, Inc | C6: Funding #1 | D6: TRL | E6: ECF2 | F6: 1 | G6: Active | H6: 240000 | I6: 160000 | J6: 4 | K6: =D6&" · "&E6&" · #"&F6 -> TRL · ECF2 · #1
A7: faba7e04-c78f-50c8-a5f2-f10fd4e5400d | B7: Sunpath Microgrids | C7: Funding #2 | D7: CGA | E7: ECF2 | F7: 2 | G7: Active | H7: 400000 | I7: 400000 | J7: 15 | K7: =D7&" · "&E7&" · #"&F7 -> CGA · ECF2 · #2
A8: b662f24b-b65d-533e-bfa9-6df5d61a8372 | B8: Northwind Solar | C8: Funding #1 | D8: CGA | E8: ECF1 | F8: 1 | G8: Active | H8: 1648000 | I8: 478105 | J8: 31 | K8: =D8&" · "&E8&" · #"&F8 -> CGA · ECF1 · #1
A9: caa72316-ceb7-5244-bf17-907cfa7d4856 | B9: Kinetiq | C9: Funding #1 | D9: RBF | E9: ECF1 | F9: 1 | G9: Active | H9: 400000 | I9: 12000 | J9: 44 | K9: =D9&" · "&E9&" · #"&F9 -> RBF · ECF1 · #1
